YandexHome/__init__.py
YandexHome/device.py
YandexHome/group.py
YandexHome/household.py
YandexHome/room.py
YandexHome/scenario.py
YandexHome-0.1.26.dist-info/METADATA
YandexHome-0.1.26.dist-info/WHEEL
YandexHome-0.1.26.dist-info/top_level.txt
YandexHome-0.1.26.dist-info/RECORD
