Metadata-Version: 2.1
Name: YandexHome
Version: 0.1.26
Summary: Yandex Умный Home
Author: ArtyomK
Requires-Python: >=3.10
Requires-Dist: aiohttp
Requires-Dist: flask[async]
Requires-Dist: asyncio
